[
  {
    "name": "Afghanistan",
    "continent": "Asia",
    "code": "AF",
    "alpha_3": "AFG",
    "dest_id": 1
  },
  {
    "name": "Aland Islands",
    "continent": "Europe",
    "code": "AX",
    "alpha_3": "ALA",
    "dest_id": 2990
  },
  {
    "name": "Albania",
    "continent": "Europe",
    "code": "AL",
    "alpha_3": "ALB",
    "dest_id": 2
  },
  {
    "name": "Algeria",
    "continent": "Africa",
    "code": "DZ",
    "alpha_3": "DZA",
    "dest_id": 3
  },
  {
    "name": "American Samoa",
    "continent": "Oceania",
    "code": "AS",
    "alpha_3": "ASM",
    "dest_id": 4
  },
  {
    "name": "Andorra",
    "continent": "Europe",
    "code": "AD",
    "alpha_3": "AND",
    "dest_id": 5
  },
  {
    "name": "Angola",
    "continent": "Africa",
    "code": "AO",
    "alpha_3": "AGO",
    "dest_id": 6
  },
  {
    "name": "Anguilla",
    "continent": "North America",
    "code": "AI",
    "alpha_3": "AIA",
    "dest_id": 7
  },
  {
    "name": "Antigua and Barbuda",
    "continent": "North America",
    "code": "AG",
    "alpha_3": "ATG",
    "dest_id": 9
  },
  {
    "name": "Argentina",
    "continent": "South America",
    "code": "AR",
    "alpha_3": "ARG",
    "dest_id": 10
  },
  {
    "name": "Armenia",
    "continent": "Asia",
    "code": "AM",
    "alpha_3": "ARM",
    "dest_id": 11
  },
  {
    "name": "Aruba",
    "continent": "North America",
    "code": "AW",
    "alpha_3": "ABW",
    "dest_id": 12
  },
  {
    "name": "Australia",
    "continent": "Oceania",
    "code": "AU",
    "alpha_3": "AUS",
    "dest_id": 13
  },
  {
    "name": "Austria",
    "continent": "Europe",
    "code": "AT",
    "alpha_3": "AUT",
    "dest_id": 14
  },
  {
    "name": "Azerbaijan",
    "continent": "Asia",
    "code": "AZ",
    "alpha_3": "AZE",
    "dest_id": 15
  },
  {
    "name": "Bahamas",
    "continent": "North America",
    "code": "BS",
    "alpha_3": "BHS",
    "dest_id": 16
  },
  {
    "name": "Bahrain",
    "continent": "Asia",
    "code": "BH",
    "alpha_3": "BHR",
    "dest_id": 17
  },
  {
    "name": "Bangladesh",
    "continent": "Asia",
    "code": "BD",
    "alpha_3": "BGD",
    "dest_id": 18
  },
  {
    "name": "Barbados",
    "continent": "North America",
    "code": "BB",
    "alpha_3": "BRB",
    "dest_id": 19
  },
  {
    "name": "Belarus",
    "continent": "Europe",
    "code": "BY",
    "alpha_3": "BLR",
    "dest_id": 20
  },
  {
    "name": "Belgium",
    "continent": "Europe",
    "code": "BE",
    "alpha_3": "BEL",
    "dest_id": 21
  },
  {
    "name": "Belize",
    "continent": "North America",
    "code": "BZ",
    "alpha_3": "BLZ",
    "dest_id": 22
  },
  {
    "name": "Benin",
    "continent": "Africa",
    "code": "BJ",
    "alpha_3": "BEN",
    "dest_id": 23
  },
  {
    "name": "Bermuda",
    "continent": "North America",
    "code": "BM",
    "alpha_3": "BMU",
    "dest_id": 24
  },
  {
    "name": "Bhutan",
    "continent": "Asia",
    "code": "BT",
    "alpha_3": "BTN",
    "dest_id": 25
  },
  {
    "name": "Bolivia",
    "continent": "South America",
    "code": "BO",
    "alpha_3": "BOL",
    "dest_id": 26
  },
  {
    "name": "Bonaire, Sint Eustatius and Saba",
    "continent": "North America",
    "code": "BQ",
    "alpha_3": "BES",
    "dest_id": 2614
  },
  {
    "name": "Bosnia and Herzegovina",
    "continent": "Europe",
    "code": "BA",
    "alpha_3": "BIH",
    "dest_id": 27
  },
  {
    "name": "Botswana",
    "continent": "Africa",
    "code": "BW",
    "alpha_3": "BWA",
    "dest_id": 28
  },
  {
    "name": "Brazil",
    "continent": "South America",
    "code": "BR",
    "alpha_3": "BRA",
    "dest_id": 30
  },
  {
    "name": "Brunei Darussalam",
    "continent": "Asia",
    "code": "BN",
    "alpha_3": "BRN",
    "dest_id": 32
  },
  {
    "name": "Bulgaria",
    "continent": "Europe",
    "code": "BG",
    "alpha_3": "BGR",
    "dest_id": 33
  },
  {
    "name": "Burkina Faso",
    "continent": "Africa",
    "code": "BF",
    "alpha_3": "BFA",
    "dest_id": 34
  },
  {
    "name": "Burundi",
    "continent": "Africa",
    "code": "BI",
    "alpha_3": "BDI",
    "dest_id": 35
  },
  {
    "name": "Cambodia",
    "continent": "Asia",
    "code": "KH",
    "alpha_3": "KHM",
    "dest_id": 36
  },
  {
    "name": "Cameroon",
    "continent": "Africa",
    "code": "CM",
    "alpha_3": "CMR",
    "dest_id": 37
  },
  {
    "name": "Canada",
    "continent": "North America",
    "code": "CA",
    "alpha_3": "CAN",
    "dest_id": 38
  },
  {
    "name": "Cape Verde",
    "continent": "Africa",
    "code": "CV",
    "alpha_3": "CPV",
    "dest_id": 39
  },
  {
    "name": "Cayman Islands",
    "continent": "North America",
    "code": "KY",
    "alpha_3": "CYM",
    "dest_id": 40
  },
  {
    "name": "Central African Republic",
    "continent": "Africa",
    "code": "CF",
    "alpha_3": "CAF",
    "dest_id": 41
  },
  {
    "name": "Chad",
    "continent": "Africa",
    "code": "TD",
    "alpha_3": "TCD",
    "dest_id": 42
  },
  {
    "name": "Chile",
    "continent": "South America",
    "code": "CL",
    "alpha_3": "CHL",
    "dest_id": 43
  },
  {
    "name": "China",
    "continent": "Asia",
    "code": "CN",
    "alpha_3": "CHN",
    "dest_id": 44
  },
  {
    "name": "Colombia",
    "continent": "South America",
    "code": "CO",
    "alpha_3": "COL",
    "dest_id": 47
  },
  {
    "name": "Comoros",
    "continent": "Africa",
    "code": "KM",
    "alpha_3": "COM",
    "dest_id": 48
  },
  {
    "name": "Congo",
    "continent": "Africa",
    "code": "CG",
    "alpha_3": "COG",
    "dest_id": 49
  },
  {
    "name": "Congo, Democratic Republic of the Congo",
    "continent": "Africa",
    "code": "CD",
    "alpha_3": "COD",
    "dest_id": 50
  },
  {
    "name": "Cook Islands",
    "continent": "Oceania",
    "code": "CK",
    "alpha_3": "COK",
    "dest_id": 51
  },
  {
    "name": "Costa Rica",
    "continent": "North America",
    "code": "CR",
    "alpha_3": "CRI",
    "dest_id": 52
  },
  {
    "name": "Cote D'Ivoire",
    "continent": "Africa",
    "code": "CI",
    "alpha_3": "CIV",
    "dest_id": 53
  },
  {
    "name": "Croatia",
    "continent": "Europe",
    "code": "HR",
    "alpha_3": "HRV",
    "dest_id": 54
  },
  {
    "name": "Cuba",
    "continent": "North America",
    "code": "CU",
    "alpha_3": "CUB",
    "dest_id": 243
  },
  {
    "name": "Curacao",
    "continent": "North America",
    "code": "CW",
    "alpha_3": "CUW",
    "dest_id": 252
  },
  {
    "name": "Cyprus",
    "continent": "Asia",
    "code": "CY",
    "alpha_3": "CYP",
    "dest_id": 55
  },
  {
    "name": "Czech Republic",
    "continent": "Europe",
    "code": "CZ",
    "alpha_3": "CZE",
    "dest_id": 56
  },
  {
    "name": "Denmark",
    "continent": "Europe",
    "code": "DK",
    "alpha_3": "DNK",
    "dest_id": 57
  },
  {
    "name": "Djibouti",
    "continent": "Africa",
    "code": "DJ",
    "alpha_3": "DJI",
    "dest_id": 58
  },
  {
    "name": "Dominica",
    "continent": "North America",
    "code": "DM",
    "alpha_3": "DMA",
    "dest_id": 59
  },
  {
    "name": "Dominican Republic",
    "continent": "North America",
    "code": "DO",
    "alpha_3": "DOM",
    "dest_id": 60
  },
  {
    "name": "Ecuador",
    "continent": "South America",
    "code": "EC",
    "alpha_3": "ECU",
    "dest_id": 62
  },
  {
    "name": "Egypt",
    "continent": "Africa",
    "code": "EG",
    "alpha_3": "EGY",
    "dest_id": 63
  },
  {
    "name": "El Salvador",
    "continent": "North America",
    "code": "SV",
    "alpha_3": "SLV",
    "dest_id": 64
  },
  {
    "name": "Equatorial Guinea",
    "continent": "Africa",
    "code": "GQ",
    "alpha_3": "GNQ",
    "dest_id": 65
  },
  {
    "name": "Eritrea",
    "continent": "Africa",
    "code": "ER",
    "alpha_3": "ERI",
    "dest_id": 66
  },
  {
    "name": "Estonia",
    "continent": "Europe",
    "code": "EE",
    "alpha_3": "EST",
    "dest_id": 67
  },
  {
    "name": "Ethiopia",
    "continent": "Africa",
    "code": "ET",
    "alpha_3": "ETH",
    "dest_id": 68
  },
  {
    "name": "Falkland Islands (Malvinas)",
    "continent": "South America",
    "code": "FK",
    "alpha_3": "FLK",
    "dest_id": 69
  },
  {
    "name": "Faroe Islands",
    "continent": "Europe",
    "code": "FO",
    "alpha_3": "FRO",
    "dest_id": 70
  },
  {
    "name": "Fiji",
    "continent": "Oceania",
    "code": "FJ",
    "alpha_3": "FJI",
    "dest_id": 71
  },
  {
    "name": "Finland",
    "continent": "Europe",
    "code": "FI",
    "alpha_3": "FIN",
    "dest_id": 72
  },
  {
    "name": "France",
    "continent": "Europe",
    "code": "FR",
    "alpha_3": "FRA",
    "dest_id": 73
  },
  {
    "name": "French Guiana",
    "continent": "South America",
    "code": "GF",
    "alpha_3": "GUF",
    "dest_id": 74
  },
  {
    "name": "French Polynesia",
    "continent": "Oceania",
    "code": "PF",
    "alpha_3": "PYF",
    "dest_id": 75
  },
  {
    "name": "Gabon",
    "continent": "Africa",
    "code": "GA",
    "alpha_3": "GAB",
    "dest_id": 77
  },
  {
    "name": "Gambia",
    "continent": "Africa",
    "code": "GM",
    "alpha_3": "GMB",
    "dest_id": 78
  },
  {
    "name": "Georgia",
    "continent": "Asia",
    "code": "GE",
    "alpha_3": "GEO",
    "dest_id": 79
  },
  {
    "name": "Germany",
    "continent": "Europe",
    "code": "DE",
    "alpha_3": "DEU",
    "dest_id": 80
  },
  {
    "name": "Ghana",
    "continent": "Africa",
    "code": "GH",
    "alpha_3": "GHA",
    "dest_id": 81
  },
  {
    "name": "Gibraltar",
    "continent": "Europe",
    "code": "GI",
    "alpha_3": "GIB",
    "dest_id": 82
  },
  {
    "name": "Greece",
    "continent": "Europe",
    "code": "GR",
    "alpha_3": "GRC",
    "dest_id": 83
  },
  {
    "name": "Greenland",
    "continent": "North America",
    "code": "GL",
    "alpha_3": "GRL",
    "dest_id": 84
  },
  {
    "name": "Grenada",
    "continent": "North America",
    "code": "GD",
    "alpha_3": "GRD",
    "dest_id": 85
  },
  {
    "name": "Guadeloupe",
    "continent": "North America",
    "code": "GP",
    "alpha_3": "GLP",
    "dest_id": 86
  },
  {
    "name": "Guam",
    "continent": "Oceania",
    "code": "GU",
    "alpha_3": "GUM",
    "dest_id": 87
  },
  {
    "name": "Guatemala",
    "continent": "North America",
    "code": "GT",
    "alpha_3": "GTM",
    "dest_id": 88
  },
  {
    "name": "Guinea",
    "continent": "Africa",
    "code": "GN",
    "alpha_3": "GIN",
    "dest_id": 89
  },
  {
    "name": "Guinea-Bissau",
    "continent": "Africa",
    "code": "GW",
    "alpha_3": "GNB",
    "dest_id": 90
  },
  {
    "name": "Guyana",
    "continent": "South America",
    "code": "GY",
    "alpha_3": "GUY",
    "dest_id": 91
  },
  {
    "name": "Haiti",
    "continent": "North America",
    "code": "HT",
    "alpha_3": "HTI",
    "dest_id": 92
  },
  {
    "name": "Honduras",
    "continent": "North America",
    "code": "HN",
    "alpha_3": "HND",
    "dest_id": 94
  },
  {
    "name": "Hong Kong",
    "continent": "Asia",
    "code": "HK",
    "alpha_3": "HKG",
    "dest_id": 95
  },
  {
    "name": "Hungary",
    "continent": "Europe",
    "code": "HU",
    "alpha_3": "HUN",
    "dest_id": 96
  },
  {
    "name": "Iceland",
    "continent": "Europe",
    "code": "IS",
    "alpha_3": "ISL",
    "dest_id": 97
  },
  {
    "name": "India",
    "continent": "Asia",
    "code": "IN",
    "alpha_3": "IND",
    "dest_id": 98
  },
  {
    "name": "Indonesia",
    "continent": "Asia",
    "code": "ID",
    "alpha_3": "IDN",
    "dest_id": 99
  },
  {
    "name": "Iran",
    "continent": "Asia",
    "code": "IR",
    "alpha_3": "IRN",
    "dest_id": 100
  },
  {
    "name": "Iraq",
    "continent": "Asia",
    "code": "IQ",
    "alpha_3": "IRQ",
    "dest_id": 101
  },
  {
    "name": "Ireland",
    "continent": "Europe",
    "code": "IE",
    "alpha_3": "IRL",
    "dest_id": 101
  },
  {
    "name": "Isle of Man",
    "continent": "Europe",
    "code": "IM",
    "alpha_3": "IMN",
    "dest_id": 2611
  },
  {
    "name": "Israel",
    "continent": "Asia",
    "code": "IL",
    "alpha_3": "ISR",
    "dest_id": 103
  },
  {
    "name": "Italy",
    "continent": "Europe",
    "code": "IT",
    "alpha_3": "ITA",
    "dest_id": 104
  },
  {
    "name": "Jamaica",
    "continent": "North America",
    "code": "JM",
    "alpha_3": "JAM",
    "dest_id": 105
  },
  {
    "name": "Japan",
    "continent": "Asia",
    "code": "JP",
    "alpha_3": "JPN",
    "dest_id": 106
  },
  {
    "name": "Jordan",
    "continent": "Asia",
    "code": "JO",
    "alpha_3": "JOR",
    "dest_id": 107
  },
  {
    "name": "Kazakhstan",
    "continent": "Asia",
    "code": "KZ",
    "alpha_3": "KAZ",
    "dest_id": 108
  },
  {
    "name": "Kenya",
    "continent": "Africa",
    "code": "KE",
    "alpha_3": "KEN",
    "dest_id": 109
  },
  {
    "name": "Kiribati",
    "continent": "Oceania",
    "code": "KI",
    "alpha_3": "KIR",
    "dest_id": 110
  },
  {
    "name": "South Korea",
    "continent": "Asia",
    "code": "KR",
    "alpha_3": "KOR",
    "dest_id": 112
  },
  {
    "name": "Kosovo",
    "continent": "Europe",
    "code": "XK",
    "alpha_3": "XKX",
    "dest_id": 250
  },
  {
    "name": "Kuwait",
    "continent": "Asia",
    "code": "KW",
    "alpha_3": "KWT",
    "dest_id": 113
  },
  {
    "name": "Kyrgyzstan",
    "continent": "Asia",
    "code": "KG",
    "alpha_3": "KGZ",
    "dest_id": 114
  },
  {
    "name": "Laos",
    "continent": "Asia",
    "code": "LA",
    "alpha_3": "LAO",
    "dest_id": 115
  },
  {
    "name": "Latvia",
    "continent": "Europe",
    "code": "LV",
    "alpha_3": "LVA",
    "dest_id": 116
  },
  {
    "name": "Lebanon",
    "continent": "Asia",
    "code": "LB",
    "alpha_3": "LBN",
    "dest_id": 117
  },
  {
    "name": "Lesotho",
    "continent": "Africa",
    "code": "LS",
    "alpha_3": "LSO",
    "dest_id": 118
  },
  {
    "name": "Liberia",
    "continent": "Africa",
    "code": "LR",
    "alpha_3": "LBR",
    "dest_id": 119
  },
  {
    "name": "Libya",
    "continent": "Africa",
    "code": "LY",
    "alpha_3": "LBY",
    "dest_id": 120
  },
  {
    "name": "Liechtenstein",
    "continent": "Europe",
    "code": "LI",
    "alpha_3": "LIE",
    "dest_id": 121
  },
  {
    "name": "Lithuania",
    "continent": "Europe",
    "code": "LT",
    "alpha_3": "LTU",
    "dest_id": 122
  },
  {
    "name": "Luxembourg",
    "continent": "Europe",
    "code": "LU",
    "alpha_3": "LUX",
    "dest_id": 123
  },
  {
    "name": "Macao",
    "continent": "Asia",
    "code": "MO",
    "alpha_3": "MAC",
    "dest_id": 124
  },
  {
    "name": "North Macedonia",
    "continent": "Europe",
    "code": "MK",
    "alpha_3": "MKD",
    "dest_id": 125
  },
  {
    "name": "Madagascar",
    "continent": "Africa",
    "code": "MG",
    "alpha_3": "MDG",
    "dest_id": 126
  },
  {
    "name": "Malawi",
    "continent": "Africa",
    "code": "MW",
    "alpha_3": "MWI",
    "dest_id": 127
  },
  {
    "name": "Malaysia",
    "continent": "Asia",
    "code": "MY",
    "alpha_3": "MYS",
    "dest_id": 128
  },
  {
    "name": "Maldives",
    "continent": "Asia",
    "code": "MV",
    "alpha_3": "MDV",
    "dest_id": 129
  },
  {
    "name": "Mali",
    "continent": "Africa",
    "code": "ML",
    "alpha_3": "MLI",
    "dest_id": 130
  },
  {
    "name": "Malta",
    "continent": "Europe",
    "code": "MT",
    "alpha_3": "MLT",
    "dest_id": 131
  },
  {
    "name": "Marshall Islands",
    "continent": "Oceania",
    "code": "MH",
    "alpha_3": "MHL",
    "dest_id": 132
  },
  {
    "name": "Martinique",
    "continent": "North America",
    "code": "MQ",
    "alpha_3": "MTQ",
    "dest_id": 133
  },
  {
    "name": "Mauritania",
    "continent": "Africa",
    "code": "MR",
    "alpha_3": "MRT",
    "dest_id": 134
  },
  {
    "name": "Mauritius",
    "continent": "Africa",
    "code": "MU",
    "alpha_3": "MUS",
    "dest_id": 135
  },
  {
    "name": "Mayotte",
    "continent": "Africa",
    "code": "YT",
    "alpha_3": "MYT",
    "dest_id": 136
  },
  {
    "name": "Mexico",
    "continent": "North America",
    "code": "MX",
    "alpha_3": "MEX",
    "dest_id": 137
  },
  {
    "name": "Micronesia",
    "continent": "Oceania",
    "code": "FM",
    "alpha_3": "FSM"
  },
  {
    "name": "Moldova",
    "continent": "Europe",
    "code": "MD",
    "alpha_3": "MDA"
  },
  {
    "name": "Monaco",
    "continent": "Europe",
    "code": "MC",
    "alpha_3": "MCO"
  },
  {
    "name": "Mongolia",
    "continent": "Asia",
    "code": "MN",
    "alpha_3": "MNG"
  },
  {
    "name": "Montenegro",
    "continent": "Europe",
    "code": "ME",
    "alpha_3": "MNE"
  },
  {
    "name": "Montserrat",
    "continent": "North America",
    "code": "MS",
    "alpha_3": "MSR"
  },
  {
    "name": "Morocco",
    "continent": "Africa",
    "code": "MA",
    "alpha_3": "MAR"
  },
  {
    "name": "Mozambique",
    "continent": "Africa",
    "code": "MZ",
    "alpha_3": "MOZ"
  },
  {
    "name": "Myanmar",
    "continent": "Asia",
    "code": "MM",
    "alpha_3": "MMR"
  },
  {
    "name": "Namibia",
    "continent": "Africa",
    "code": "NA",
    "alpha_3": "NAM"
  },
  {
    "name": "Nauru",
    "continent": "Oceania",
    "code": "NR",
    "alpha_3": "NRU"
  },
  {
    "name": "Nepal",
    "continent": "Asia",
    "code": "NP",
    "alpha_3": "NPL"
  },
  {
    "name": "Netherlands",
    "continent": "Europe",
    "code": "NL",
    "alpha_3": "NLD",
    "dest_id": 149
  },
  {
    "name": "Netherlands Antilles",
    "continent": "North America",
    "code": "AN",
    "alpha_3": "ANT",
    "dest_id": 150
  },
  {
    "name": "New Caledonia",
    "continent": "Oceania",
    "code": "NC",
    "alpha_3": "NCL",
    "dest_id": 151
  },
  {
    "name": "New Zealand",
    "continent": "Oceania",
    "code": "NZ",
    "alpha_3": "NZL",
    "dest_id": 152
  },
  {
    "name": "Nicaragua",
    "continent": "North America",
    "code": "NI",
    "alpha_3": "NIC",
    "dest_id": 153
  },
  {
    "name": "Niger",
    "continent": "Africa",
    "code": "NE",
    "alpha_3": "NER",
    "dest_id": 154
  },
  {
    "name": "Nigeria",
    "continent": "Africa",
    "code": "NG",
    "alpha_3": "NGA",
    "dest_id": 155
  },
  {
    "name": "Niue",
    "continent": "Oceania",
    "code": "NU",
    "alpha_3": "NIU",
    "dest_id": 156
  },
  {
    "name": "Norfolk Island",
    "continent": "Oceania",
    "code": "NF",
    "alpha_3": "NFK",
    "dest_id": 157
  },
  {
    "name": "Northern Mariana Islands",
    "continent": "Oceania",
    "code": "MP",
    "alpha_3": "MNP",
    "dest_id": 158
  },
  {
    "name": "Norway",
    "continent": "Europe",
    "code": "NO",
    "alpha_3": "NOR",
    "dest_id": 159
  },
  {
    "name": "Oman",
    "continent": "Asia",
    "code": "OM",
    "alpha_3": "OMN",
    "dest_id": 160
  },
  {
    "name": "Pakistan",
    "continent": "Asia",
    "code": "PK",
    "alpha_3": "PAK",
    "dest_id": 161
  },
  {
    "name": "Palau",
    "continent": "Oceania",
    "code": "PW",
    "alpha_3": "PLW",
    "dest_id": 162
  },
  {
    "name": "Palestinian Territory",
    "continent": "Asia",
    "code": "PS",
    "alpha_3": "PSE",
    "dest_id": 163
  },
  {
    "name": "Panama",
    "continent": "North America",
    "code": "PA",
    "alpha_3": "PAN",
    "dest_id": 164
  },
  {
    "name": "Papua New Guinea",
    "continent": "Oceania",
    "code": "PG",
    "alpha_3": "PNG",
    "dest_id": 165
  },
  {
    "name": "Paraguay",
    "continent": "South America",
    "code": "PY",
    "alpha_3": "PRY",
    "dest_id": 166
  },
  {
    "name": "Peru",
    "continent": "South America",
    "code": "PE",
    "alpha_3": "PER",
    "dest_id": 167
  },
  {
    "name": "Philippines",
    "continent": "Asia",
    "code": "PH",
    "alpha_3": "PHL",
    "dest_id": 168
  },
  {
    "name": "Pitcairn",
    "continent": "Oceania",
    "code": "PN",
    "alpha_3": "PCN",
    "dest_id": 169
  },
  {
    "name": "Poland",
    "continent": "Europe",
    "code": "PL",
    "alpha_3": "POL",
    "dest_id": 170
  },
  {
    "name": "Portugal",
    "continent": "Europe",
    "code": "PT",
    "alpha_3": "PRT",
    "dest_id": 171
  },
  {
    "name": "Puerto Rico",
    "continent": "North America",
    "code": "PR",
    "alpha_3": "PRI",
    "dest_id": 172
  },
  {
    "name": "Qatar",
    "continent": "Asia",
    "code": "QA",
    "alpha_3": "QAT",
    "dest_id": 173
  },
  {
    "name": "Réunion",
    "continent": "Africa",
    "code": "RE",
    "alpha_3": "REU"
  },
  {
    "name": "Romania",
    "continent": "Europe",
    "code": "RO",
    "alpha_3": "ROM"
  },
  {
    "name": "Russia",
    "continent": "Asia",
    "code": "RU",
    "alpha_3": "RUS"
  },
  {
    "name": "Rwanda",
    "continent": "Africa",
    "code": "RW",
    "alpha_3": "RWA"
  },
  {
    "name": "Saint Barthelemy",
    "continent": "North America",
    "code": "BL",
    "alpha_3": "BLM",
    "dest_id": 245
  },
  {
    "name": "Saint Helena",
    "continent": "Africa",
    "code": "SH",
    "alpha_3": "SHN",
    "dest_id": 178
  },
  {
    "name": "Saint Kitts and Nevis",
    "continent": "North America",
    "code": "KN",
    "alpha_3": "KNA",
    "dest_id": 179
  },
  {
    "name": "Saint Lucia",
    "continent": "North America",
    "code": "LC",
    "alpha_3": "LCA",
    "dest_id": 180
  },
  {
    "name": "Saint Martin",
    "continent": "North America",
    "code": "MF",
    "alpha_3": "MAF",
    "dest_id": 240
  },
  {
    "name": "Saint Pierre and Miquelon",
    "continent": "North America",
    "code": "PM",
    "alpha_3": "SPM"
  },
  {
    "name": "Saint Vincent and the Grenadines",
    "continent": "North America",
    "code": "VC",
    "alpha_3": "VCT"
  },
  {
    "name": "Samoa",
    "continent": "Oceania",
    "code": "WS",
    "alpha_3": "WSM"
  },
  {
    "name": "San Marino",
    "continent": "Europe",
    "code": "SM",
    "alpha_3": "SMR"
  },
  {
    "name": "Sao Tome and Principe",
    "continent": "Africa",
    "code": "ST",
    "alpha_3": "STP"
  },
  {
    "name": "Saudi Arabia",
    "continent": "Asia",
    "code": "SA",
    "alpha_3": "SAU"
  },
  {
    "name": "Senegal",
    "continent": "Africa",
    "code": "SN",
    "alpha_3": "SEN"
  },
  {
    "name": "Serbia",
    "continent": "Europe",
    "code": "RS",
    "alpha_3": "SRB"
  },
  {
    "name": "Serbia and Montenegro",
    "continent": "Europe",
    "code": "CS",
    "alpha_3": "SCG"
  },
  {
    "name": "Seychelles",
    "continent": "Africa",
    "code": "SC",
    "alpha_3": "SYC"
  },
  {
    "name": "Sierra Leone",
    "continent": "Africa",
    "code": "SL",
    "alpha_3": "SLE"
  },
  {
    "name": "Singapore",
    "continent": "Asia",
    "code": "SG",
    "alpha_3": "SGP"
  },
  {
    "name": "Sint Maarten",
    "continent": "North America",
    "code": "SX",
    "alpha_3": "SXM"
  },
  {
    "name": "Slovakia",
    "continent": "Europe",
    "code": "SK",
    "alpha_3": "SVK"
  },
  {
    "name": "Slovenia",
    "continent": "Europe",
    "code": "SI",
    "alpha_3": "SVN"
  },
  {
    "name": "Solomon Islands",
    "continent": "Oceania",
    "code": "SB",
    "alpha_3": "SLB"
  },
  {
    "name": "Somalia",
    "continent": "Africa",
    "code": "SO",
    "alpha_3": "SOM"
  },
  {
    "name": "South Africa",
    "continent": "Africa",
    "code": "ZA",
    "alpha_3": "ZAF",
    "dest_id": 195
  },
  {
    "name": "South Sudan",
    "continent": "Africa",
    "code": "SS",
    "alpha_3": "SSD",
    "dest_id": 508
  },
  {
    "name": "Spain",
    "continent": "Europe",
    "code": "ES",
    "alpha_3": "ESP",
    "dest_id": 197
  },
  {
    "name": "Sri Lanka",
    "continent": "Asia",
    "code": "LK",
    "alpha_3": "LKA",
    "dest_id": 198
  },
  {
    "name": "Suriname",
    "continent": "South America",
    "code": "SR",
    "alpha_3": "SUR",
    "dest_id": 200
  },
  {
    "name": "Swaziland",
    "continent": "Africa",
    "code": "SZ",
    "alpha_3": "SWZ",
    "dest_id": 202
  },
  {
    "name": "Sweden",
    "continent": "Europe",
    "code": "SE",
    "alpha_3": "SWE",
    "dest_id": 203
  },
  {
    "name": "Switzerland",
    "continent": "Europe",
    "code": "CH",
    "alpha_3": "CHE",
    "dest_id": 204
  },
  {
    "name": "Taiwan",
    "continent": "Asia",
    "code": "TW",
    "alpha_3": "TWN",
    "dest_id": 206
  },
  {
    "name": "Tajikistan",
    "continent": "Asia",
    "code": "TJ",
    "alpha_3": "TJK",
    "dest_id": 207
  },
  {
    "name": "Tanzania",
    "continent": "Africa",
    "code": "TZ",
    "alpha_3": "TZA",
    "dest_id": 208
  },
  {
    "name": "Thailand",
    "continent": "Asia",
    "code": "TH",
    "alpha_3": "THA",
    "dest_id": 209
  },
  {
    "name": "Timor-Leste",
    "continent": "Asia",
    "code": "TL",
    "alpha_3": "TLS",
    "dest_id": 61
  },
  {
    "name": "Togo",
    "continent": "Africa",
    "code": "TG",
    "alpha_3": "TGO",
    "dest_id": 210
  },
  {
    "name": "Tonga",
    "continent": "Oceania",
    "code": "TO",
    "alpha_3": "TON",
    "dest_id": 212
  },
  {
    "name": "Trinidad and Tobago",
    "continent": "North America",
    "code": "TT",
    "alpha_3": "TTO",
    "dest_id": 213
  },
  {
    "name": "Tunisia",
    "continent": "Africa",
    "code": "TN",
    "alpha_3": "TUN",
    "dest_id": 214
  },
  {
    "name": "Turkey",
    "continent": "Asia",
    "code": "TR",
    "alpha_3": "TUR",
    "dest_id": 215
  },
  {
    "name": "Turkmenistan",
    "continent": "Asia",
    "code": "TM",
    "alpha_3": "TKM",
    "dest_id": 216
  },
  {
    "name": "Turks and Caicos Islands",
    "continent": "North America",
    "code": "TC",
    "alpha_3": "TCA",
    "dest_id": 217
  },
  {
    "name": "Uganda",
    "continent": "Africa",
    "code": "UG",
    "alpha_3": "UGA",
    "dest_id": 219
  },
  {
    "name": "Ukraine",
    "continent": "Europe",
    "code": "UA",
    "alpha_3": "UKR",
    "dest_id": 220
  },
  {
    "name": "United Arab Emirates",
    "continent": "Asia",
    "code": "AE",
    "alpha_3": "ARE",
    "dest_id": 221
  },
  {
    "name": "United Kingdom",
    "continent": "Europe",
    "code": "GB",
    "alpha_3": "GBR",
    "dest_id": 222
  },
  {
    "name": "United States",
    "continent": "North America",
    "code": "US",
    "alpha_3": "USA",
    "dest_id": 244
  },
  {
    "name": "Uruguay",
    "continent": "South America",
    "code": "UY",
    "alpha_3": "URY",
    "dest_id": 225
  },
  {
    "name": "Uzbekistan",
    "continent": "Asia",
    "code": "UZ",
    "alpha_3": "UZB",
    "dest_id": 226
  },
  {
    "name": "Vanuatu",
    "continent": "Oceania",
    "code": "VU",
    "alpha_3": "VUT",
    "dest_id": 227
  },
  {
    "name": "Venezuela",
    "continent": "South America",
    "code": "VE",
    "alpha_3": "VEN",
    "dest_id": 229
  },
  {
    "name": "Vietnam",
    "continent": "Asia",
    "code": "VN",
    "alpha_3": "VNM",
    "dest_id": 230
  },
  {
    "name": "Virgin Islands, British",
    "continent": "North America",
    "code": "VG",
    "alpha_3": "VGB",
    "dest_id": 231
  },
  {
    "name": "Virgin Islands, U.S.",
    "continent": "North America",
    "code": "VI",
    "alpha_3": "VIR",
    "dest_id": 232
  },
  {
    "name": "Yemen",
    "continent": "Asia",
    "code": "YE",
    "alpha_3": "YEM",
    "dest_id": 235
  },
  {
    "name": "Zambia",
    "continent": "Africa",
    "code": "ZM",
    "alpha_3": "ZMB",
    "dest_id": 236
  },
  {
    "name": "Zimbabwe",
    "continent": "Africa",
    "code": "ZW",
    "alpha_3": "ZWE",
    "dest_id": 237
  }
]
